pyChatGPTH/Auth0.py
pyChatGPTH/__init__.py
pyChatGPTH/__main__.py
pyChatGPTH/pyChatGPT.py
pyChatGPTH-2.0.dist-info/LICENSE
pyChatGPTH-2.0.dist-info/METADATA
pyChatGPTH-2.0.dist-info/WHEEL
pyChatGPTH-2.0.dist-info/top_level.txt
pyChatGPTH-2.0.dist-info/RECORD
