Metadata-Version: 2.1
Name: pyChatGPTH
Version: 2.0
Summary: An unofficial Python wrapper for OpenAI's ChatGPT API for HEROKU
Author-email: wanne87 <wanne21901@gmail.com>
Project-URL: Homepage, https://github.com/wanne88/pyChatGPT
Project-URL: Bug Tracker, https://github.com/wanne88/pyChatGPT/issues
Classifier: Programming Language :: Python :: 3
Classifier: License :: OSI Approved :: GNU General Public License v3 (GPLv3)
Classifier: Operating System :: OS Independent
Requires-Python: >=3.7
License-File: LICENSE
Requires-Dist: undetected-chromedriver (>=3.2.1)
Requires-Dist: markdownify (>=0.11.6)
